{"file":"auth-DIhDKz73.js","mappings":";;;;;;;;;;;;;;;;;AAyFa,iBAAA;AACE,cAAA;AAGf,UAAM,QAAQ,SAAS,EAAE,OAAO,IAAI,UAAU,IAAI;AAClD,UAAM,aAAa,IAAI,EAAE;AACzB,UAAM,eAAe,IAAI,KAAK;AAgB9B,UAAM,MAAM,SAAS,EAAE,UAAU,IAAI,OAAO,IAAI,UAAU,IAAI,SAAS,GAAA,CAAI;AAC3E,UAAM,WAAW,IAAI,EAAE;AACvB,UAAM,aAAa,IAAI,KAAK;AAE5B,UAAM,WAAW,SAAS,MAAM;AAC9B,YAAM,IAAI,IAAI;AACd,UAAI,IAAI;AACR,UAAI,EAAE,UAAU,EAAG;AACnB,UAAI,QAAQ,KAAK,CAAC,EAAG;AACrB,UAAI,QAAQ,KAAK,CAAC,EAAG;AACrB,UAAI,eAAe,KAAK,CAAC,EAAG;AAC5B,aAAO;AAAA,IACT,CAAC;;mBA1HMA,eAAAC,WAAA,EAAA,OAAM,YAAA,GAAW,MAAA,CAAA,8WAgBEC,cAAA,SAAAC,MAAA,KAAA,EAAM,KAAK,mGAIXD,cAAA,SAAAC,MAAA,KAAA,EAAM,QAAQ;UAGrBA,MAAA,UAAA,GAAU;0FACiBA,MAAA,UAAA,CAAU,CAAA,QAAA;AAAA;;;+EAEMA,MAAA,YAAA,CAAY,IAAA,cAAA,mDACjCA,MAAA,YAAA,IAAY,cAAA,OAAA,snBA0B3BD,cAAA,SAAAC,MAAA,GAAA,EAAI,QAAQ,0JAKZD,cAAA,SAAAC,MAAA,GAAA,EAAI,KAAK,mGAITD,cAAA,SAAAC,MAAA,GAAA,EAAI,QAAQ;AAETC,oBAAA,IAAL,MAAC;AAAmC,cAAA,eAAAC,eAAA,CAAA,KAAKF,MAAA,QAAA,IAAQ,YAAA,YAAA,IAAA,CAAA,CAAA,UAAA;AAAA;;UAEpDA,MAAA,QAAA,KAAQ,GAAA;;;;;AAMH,YAAA,mEAAAD,cAAA,SAAAC,MAAA,GAAA,EAAI,OAAO,CAAA,gDAAA;UAElBA,MAAA,QAAA,GAAQ;0FACmBA,MAAA,QAAA,CAAQ,CAAA,QAAA;AAAA;;;+EAEQA,MAAA,UAAA,CAAU,IAAA,cAAA,qDAC7BA,MAAA,UAAA,IAAU,eAAA,oBAAA;;;;;;;;;;","names":["_ssrRenderAttrs","_mergeProps","_ssrRenderAttr","_unref","_ssrRenderList","_ssrRenderClass"],"sources":["../../../../pages/auth.vue"],"sourcesContent":["<template>\n  <div class=\"auth-wrap\">\n    <!-- Форма входа -->\n    <div class=\"screen\">\n      <div class=\"auth-top\">\n        <div class=\"logo\">\n          <span class=\"mark\"><i class=\"ti ti-paw-filled\" /></span>\n          LPS коллекционер\n        </div>\n      </div>\n      <div class=\"auth-hero\">\n        <div class=\"auth-title\">С возвращением 👋</div>\n        <div class=\"auth-sub\">Войдите, чтобы управлять своей коллекцией</div>\n      </div>\n      <div class=\"auth-body\">\n        <div class=\"field\">\n          <label>Email</label>\n          <input v-model=\"login.email\" type=\"email\" placeholder=\"your@email.com\">\n        </div>\n        <div class=\"field\">\n          <label>Пароль</label>\n          <input v-model=\"login.password\" type=\"password\" placeholder=\"••••••••\">\n          <div class=\"field-hint link\">Забыли пароль?</div>\n        </div>\n        <div v-if=\"loginError\" class=\"error-msg\">\n          <i class=\"ti ti-alert-circle\" /> {{ loginError }}\n        </div>\n        <button class=\"btn btn-primary btn-submit\" :disabled=\"loginPending\" @click=\"doLogin\">\n          <i class=\"ti ti-login-2\" /> {{ loginPending ? 'Входим...' : 'Войти' }}\n        </button>\n        <div class=\"divider-row\">\n          <div class=\"divider-line\" /><span class=\"divider-txt\">или</span><div class=\"divider-line\" />\n        </div>\n        <button class=\"btn btn-ghost btn-google\">\n          <i class=\"ti ti-brand-google\" /> Войти через Google\n        </button>\n      </div>\n    </div>\n\n    <!-- Форма регистрации -->\n    <div class=\"screen\">\n      <div class=\"auth-top\">\n        <div class=\"logo\">\n          <span class=\"mark\"><i class=\"ti ti-paw-filled\" /></span>\n          LPS коллекционер\n        </div>\n      </div>\n      <div class=\"auth-hero\">\n        <div class=\"auth-title\">Создать аккаунт</div>\n        <div class=\"auth-sub\">Начните вести учёт коллекции прямо сейчас</div>\n      </div>\n      <div class=\"auth-body\">\n        <div class=\"field\">\n          <label>Имя пользователя</label>\n          <input v-model=\"reg.username\" type=\"text\" placeholder=\"lps_collector\">\n          <div class=\"field-hint\">Будет отображаться в профиле</div>\n        </div>\n        <div class=\"field\">\n          <label>Email</label>\n          <input v-model=\"reg.email\" type=\"email\" placeholder=\"your@email.com\">\n        </div>\n        <div class=\"field\">\n          <label>Пароль</label>\n          <input v-model=\"reg.password\" type=\"password\" placeholder=\"••••••••\">\n          <div class=\"strength\">\n            <div v-for=\"i in 4\" :key=\"i\" class=\"sb\" :class=\"i <= strength ? 'sb-fill' : 'sb-empty'\" />\n          </div>\n          <div v-if=\"strength >= 3\" class=\"strength-lbl\">\n            <i class=\"ti ti-shield-check\" /> Надёжный пароль\n          </div>\n        </div>\n        <div class=\"field\">\n          <label>Подтвердите пароль</label>\n          <input v-model=\"reg.confirm\" type=\"password\" placeholder=\"••••••••\">\n        </div>\n        <div v-if=\"regError\" class=\"error-msg\">\n          <i class=\"ti ti-alert-circle\" /> {{ regError }}\n        </div>\n        <button class=\"btn btn-primary btn-submit\" :disabled=\"regPending\" @click=\"doRegister\">\n          <i class=\"ti ti-user-plus\" /> {{ regPending ? 'Создаём...' : 'Зарегистрироваться' }}\n        </button>\n      </div>\n    </div>\n  </div>\n</template>\n\n<script setup lang=\"ts\">\ndefinePageMeta({ layout: false }) // своя раскладка без nav/footer\n\nconst auth = useAuthStore()\nconst router = useRouter()\n\n// — Вход —\nconst login = reactive({ email: '', password: '' })\nconst loginError = ref('')\nconst loginPending = ref(false)\n\nasync function doLogin() {\n  loginError.value = ''\n  loginPending.value = true\n  try {\n    await auth.login(login)\n    router.push('/')\n  } catch (e: any) {\n    loginError.value = e?.data?.message ?? 'Ошибка входа'\n  } finally {\n    loginPending.value = false\n  }\n}\n\n// — Регистрация —\nconst reg = reactive({ username: '', email: '', password: '', confirm: '' })\nconst regError = ref('')\nconst regPending = ref(false)\n\nconst strength = computed(() => {\n  const p = reg.password\n  let s = 0\n  if (p.length >= 8) s++\n  if (/[A-Z]/.test(p)) s++\n  if (/[0-9]/.test(p)) s++\n  if (/[^A-Za-z0-9]/.test(p)) s++\n  return s\n})\n\nasync function doRegister() {\n  regError.value = ''\n  if (reg.password !== reg.confirm) { regError.value = 'Пароли не совпадают'; return }\n  regPending.value = true\n  try {\n    await auth.register({ username: reg.username, email: reg.email, password: reg.password })\n    router.push('/')\n  } catch (e: any) {\n    regError.value = e?.data?.message ?? 'Ошибка регистрации'\n  } finally {\n    regPending.value = false\n  }\n}\n</script>\n\n<style lang=\"scss\">\nbody { padding: 28px 24px; }\n\n.auth-wrap {\n  display: grid;\n  grid-template-columns: 1fr 1fr;\n  gap: 18px;\n  max-width: 880px;\n  margin: 0 auto;\n\n  .screen { max-width: none; margin: 0; }\n}\n\n.auth-top {\n  padding: 16px 22px;\n  border-bottom: 1px solid $line;\n  display: flex;\n  align-items: center;\n  background: $bg-sunken;\n}\n\n.auth-hero {\n  position: relative;\n  padding: 26px 22px 20px;\n  overflow: hidden;\n  border-bottom: 1px solid $line;\n  background: radial-gradient(120% 130% at 0% 0%, #f3f0ff, $bg-sunken 60%);\n\n  &::before {\n    content: '';\n    position: absolute;\n    inset: 0;\n    background-image: $paw-tile;\n    opacity: .8;\n    mask-image: linear-gradient(120deg, #000, transparent 75%);\n  }\n\n  > * { position: relative; }\n}\n\n.auth-title { @include font-display(21px); color: $ink; margin-bottom: 5px; }\n.auth-sub   { font-size: 13px; color: $ink-2; line-height: 1.5; font-weight: 600; max-width: 300px; }\n.auth-body  { padding: 22px; }\n\n.field {\n  margin-bottom: 16px;\n\n  label { display: block; font-size: 12px; color: $ink-2; margin-bottom: 6px; font-weight: 700; }\n  input { @include input-base; }\n}\n\n.field-hint {\n  font-size: 11px; color: $ink-3; margin-top: 4px; font-weight: 600;\n  &.link { color: $brand; text-align: right; cursor: pointer; font-weight: 700; }\n}\n\n.btn-submit { width: 100%; padding: 12px; font-size: 14.5px; margin-top: 4px; }\n.btn-google { width: 100%; padding: 10px; }\n\n.divider-row {\n  @include flex-row(10px);\n  margin: 16px 0;\n\n  .divider-line { flex: 1; height: 1px; background: $line; }\n  .divider-txt  { font-size: 11.5px; color: $ink-3; font-weight: 700; }\n}\n\n.error-msg {\n  font-size: 11px; color: $danger; margin-bottom: 8px;\n  @include flex-row(4px);\n  font-weight: 700;\n}\n\n.strength { @include flex-row(4px); margin-top: 7px; }\n.sb { height: 4px; border-radius: $r-pill; flex: 1; }\n.sb-fill  { background: $success; }\n.sb-empty { background: $line-2; }\n.strength-lbl { font-size: 10.5px; color: $success; margin-top: 4px; font-weight: 700; @include flex-row(3px); }\n</style>\n"],"version":3}